firebolt/__init__.py
firebolt/py.typed
firebolt/async_db/__init__.py
firebolt/async_db/connection.py
firebolt/async_db/cursor.py
firebolt/client/__init__.py
firebolt/client/client.py
firebolt/client/constants.py
firebolt/client/http_backend.py
firebolt/client/resource_manager_hooks.py
firebolt/client/auth/__init__.py
firebolt/client/auth/base.py
firebolt/client/auth/client_credentials.py
firebolt/client/auth/firebolt_core.py
firebolt/client/auth/request_auth_base.py
firebolt/client/auth/service_account.py
firebolt/client/auth/token.py
firebolt/client/auth/username_password.py
firebolt/common/__init__.py
firebolt/common/_types.py
firebolt/common/base_connection.py
firebolt/common/constants.py
firebolt/common/exception.py
firebolt/common/settings.py
firebolt/common/statement_formatter.py
firebolt/common/token_storage.py
firebolt/common/urls.py
firebolt/common/util.py
firebolt/common/cursor/__init__.py
firebolt/common/cursor/base_cursor.py
firebolt/common/cursor/decorators.py
firebolt/common/cursor/statement_planners.py
firebolt/common/row_set/__init__.py
firebolt/common/row_set/base.py
firebolt/common/row_set/json_lines.py
firebolt/common/row_set/streaming_common.py
firebolt/common/row_set/types.py
firebolt/common/row_set/asynchronous/__init__.py
firebolt/common/row_set/asynchronous/base.py
firebolt/common/row_set/asynchronous/in_memory.py
firebolt/common/row_set/asynchronous/streaming.py
firebolt/common/row_set/synchronous/__init__.py
firebolt/common/row_set/synchronous/base.py
firebolt/common/row_set/synchronous/in_memory.py
firebolt/common/row_set/synchronous/streaming.py
firebolt/db/__init__.py
firebolt/db/connection.py
firebolt/db/cursor.py
firebolt/model/__init__.py
firebolt/model/engine.py
firebolt/model/V1/__init__.py
firebolt/model/V1/binding.py
firebolt/model/V1/database.py
firebolt/model/V1/engine.py
firebolt/model/V1/engine_revision.py
firebolt/model/V1/provider.py
firebolt/model/V1/region.py
firebolt/model/V2/__init__.py
firebolt/model/V2/database.py
firebolt_sdk-1.18.1.dist-info/LICENSE
firebolt_sdk-1.18.1.dist-info/METADATA
firebolt_sdk-1.18.1.dist-info/WHEEL
firebolt_sdk-1.18.1.dist-info/top_level.txt
firebolt_sdk-1.18.1.dist-info/RECORD
