Metadata-Version: 2.1
Name: firebolt_sdk
Version: 1.18.1
Summary: Python SDK for Firebolt
Home-page: https://github.com/firebolt-db/firebolt-sdk
Author: Firebolt
Author-email: support@firebolt.io
License: Apache-2.0
Project-URL: Bug Tracker, https://github.com/firebolt-db/firebolt-sdk/issues
Classifier: License :: OSI Approved :: Apache Software License
Classifier: Operating System :: OS Independent
Classifier: Programming Language :: Python :: 3
Classifier: Programming Language :: Python :: 3 :: Only
Classifier: Programming Language :: Python :: 3.9
Classifier: Programming Language :: Python :: 3.10
Classifier: Programming Language :: Python :: 3.11
Classifier: Programming Language :: Python :: 3.12
Requires-Python: >=3.9
License-File: LICENSE
Requires-Dist: aiorwlock==1.5.0
Requires-Dist: anyio>=3.7.1
Requires-Dist: appdirs>=1.4.4
Requires-Dist: appdirs-stubs>=0.1.0
Requires-Dist: async-generator>=1.10
Requires-Dist: async-property>=0.2.1
Requires-Dist: cryptography>=3.4.0
Requires-Dist: httpcore>=0.17.0
Requires-Dist: httpx[http2]>=0.19.0
Requires-Dist: pydantic[dotenv]<3.0.0,>=1.8.2
Requires-Dist: python-dateutil>=2.8.2
Requires-Dist: readerwriterlock>=1.0.9
Requires-Dist: sqlparse>=0.4.2
Requires-Dist: trio>=0.22.0
Requires-Dist: truststore>=0.10; python_version >= "3.10"
Provides-Extra: ciso8601
Requires-Dist: ciso8601==2.2.0; extra == "ciso8601"
Provides-Extra: dev
Requires-Dist: allure-pytest==2.*; extra == "dev"
Requires-Dist: devtools==0.12.2; extra == "dev"
Requires-Dist: mypy<2,>=1; extra == "dev"
Requires-Dist: pre-commit==3.5.0; extra == "dev"
Requires-Dist: psutil==7.0.0; extra == "dev"
Requires-Dist: pyfakefs<=5.6.0,>=4.5.3; extra == "dev"
Requires-Dist: pytest==8.4.1; extra == "dev"
Requires-Dist: pytest-cov==3.0.0; extra == "dev"
Requires-Dist: pytest-httpx>=0.13.0; extra == "dev"
Requires-Dist: pytest-mock==3.15.1; extra == "dev"
Requires-Dist: pytest-timeout==2.1.0; extra == "dev"
Requires-Dist: pytest-trio==0.8.0; extra == "dev"
Requires-Dist: pytest-xdist==2.5.0; extra == "dev"
Requires-Dist: trio-typing[mypy]<0.11,>=0.6; extra == "dev"
Requires-Dist: types-cryptography==3.3.18; extra == "dev"
Provides-Extra: docs
Requires-Dist: sphinx==7.*; extra == "docs"
Requires-Dist: sphinx-rtd-theme==2.*; extra == "docs"
